{
	"archive" : {},
	"artifacts" : 
	[
		{
			"path" : "tasks/rpc-io/libcoro_queue.a"
		}
	],
	"backtrace" : 1,
	"backtraceGraph" : 
	{
		"commands" : 
		[
			"add_library",
			"target_link_libraries"
		],
		"files" : 
		[
			"tasks/rpc-io/CMakeLists.txt"
		],
		"nodes" : 
		[
			{
				"file" : 0
			},
			{
				"command" : 0,
				"file" : 0,
				"line" : 257,
				"parent" : 0
			},
			{
				"command" : 1,
				"file" : 0,
				"line" : 267,
				"parent" : 0
			}
		]
	},
	"dependencies" : 
	[
		{
			"backtrace" : 2,
			"id" : "fmt::@976f4f0bee90b99ecdb6"
		},
		{
			"backtrace" : 2,
			"id" : "folly::@99b2e6160ccd356f445d"
		}
	],
	"id" : "coro_queue::@75768a65d2d6e0f2b377",
	"name" : "coro_queue",
	"nameOnDisk" : "libcoro_queue.a",
	"paths" : 
	{
		"build" : "tasks/rpc-io",
		"source" : "tasks/rpc-io"
	},
	"sourceGroups" : 
	[
		{
			"name" : "Header Files",
			"sourceIndexes" : 
			[
				0
			]
		}
	],
	"sources" : 
	[
		{
			"backtrace" : 1,
			"path" : "tasks/rpc-io/coro/queue.hpp",
			"sourceGroupIndex" : 0
		}
	],
	"type" : "STATIC_LIBRARY"
}
